pymssql/__init__.py
pymssql/__init__.pyi
pymssql/_mssql.cpython-313-aarch64-linux-gnu.so
pymssql/_mssql.pxd
pymssql/_mssql.pyi
pymssql/_mssql.pyx
pymssql/_pymssql.cpython-313-aarch64-linux-gnu.so
pymssql/_pymssql.pyi
pymssql/_pymssql.pyx
pymssql/exceptions.py
pymssql/exceptions.pyi
pymssql/py.typed
pymssql/sqlfront.pxd
pymssql/version.h
pymssql.libs/libcom_err-057ba42b.so.2.1
pymssql.libs/libcrypto-13880bfc.so.1.0.2k
pymssql.libs/libgssapi_krb5-fec99a71.so.2.2
pymssql.libs/libk5crypto-47ac5e52.so.3.1
pymssql.libs/libkeyutils-19c64d08.so.1.5
pymssql.libs/libkrb5-90a0ef7c.so.3.3
pymssql.libs/libkrb5support-73f3f43d.so.0.1
pymssql.libs/libpcre-6b975b27.so.1.2.0
pymssql.libs/libselinux-ae24b712.so.1
pymssql.libs/libssl-e50c59ab.so.1.0.2k
pymssql-2.3.11.dist-info/METADATA
pymssql-2.3.11.dist-info/WHEEL
pymssql-2.3.11.dist-info/top_level.txt
pymssql-2.3.11.dist-info/RECORD
pymssql-2.3.11.dist-info/licenses/LICENSE
pymssql-2.3.11.dist-info/sboms/auditwheel.cdx.json
