Metadata-Version: 2.4
Name: pymssql
Version: 2.3.11
Summary: DB-API interface to Microsoft SQL Server for Python. (new Cython-based version)
Author-email: Damien Churchill <damoxc@gmail.com>
Maintainer-email: Mikhail Terekhov <termim@gmail.com>
License: 		  GNU LESSER GENERAL PUBLIC LICENSE
Project-URL: homepage, https://github.com/pymssql/pymssql
Project-URL: repository, https://github.com/pymssql/pymssql
Project-URL: documentation, http://pymssql.readthedocs.io
Project-URL: Bug Tracker, https://github.com/pymssql/pymssql/issues
Project-URL: Changelog, https://github.com/pymssql/pymssql/blob/master/ChangeLog.rst
Keywords: mssql,SQL Server,database,DB-API
Platform: any
Classifier: Development Status :: 5 - Production/Stable
Classifier: Intended Audience :: Developers
Classifier: Programming Language :: Python
Classifier: Programming Language :: Python :: 3.9
Classifier: Programming Language :: Python :: 3.10
Classifier: Programming Language :: Python :: 3.11
Classifier: Programming Language :: Python :: 3.12
Classifier: Programming Language :: Python :: 3.13
Classifier: Programming Language :: Python :: 3.14
Classifier: Programming Language :: Python :: Implementation :: CPython
Classifier: Topic :: Database
Classifier: Topic :: Database :: Database Engines/Servers
Classifier: Topic :: Software Development :: Libraries :: Python Modules
Classifier: Operating System :: Microsoft :: Windows
Classifier: Operating System :: POSIX
Classifier: Operating System :: Unix
Requires-Python: >=3.9
License-File: LICENSE
Dynamic: description
Dynamic: description-content-type
Dynamic: license-file
Dynamic: platform
